dplot/__init__.py
dplot/dplot.py
dplot/parsers/__init__.py
dplot/parsers/args.py
dplot/parsers/test_args.py
dplot-0.0.3.data/scripts/dplot
dplot-0.0.3.dist-info/METADATA
dplot-0.0.3.dist-info/WHEEL
dplot-0.0.3.dist-info/top_level.txt
dplot-0.0.3.dist-info/RECORD
