Metadata-Version: 2.1
Name: dplot
Version: 0.0.3
Summary: Plots Gromacs SAXS, Pepsi-SAXS, Crysol and Debyer SWAXS intensity curves
Home-page: https://gitlab.com/w8jcik/dplot
Author: Maciej Wójcik
Author-email: w8jcik@gmail.com
License: UNKNOWN
Platform: UNKNOWN
Classifier: Programming Language :: Python :: 3
Classifier: License :: OSI Approved :: MIT License
Classifier: Operating System :: POSIX :: Linux
Requires-Dist: pandas
Requires-Dist: seaborn
Requires-Dist: matplotlib
